marketplace_handler/__init__.py
marketplace_handler/config.py
marketplace_handler/exceptions.py
marketplace_handler/logger.py
marketplace_handler/mapping.py
marketplace_handler/marketplace.py
marketplace_handler/ozon.py
marketplace_handler/schemas.py
marketplace_handler/utils.py
marketplace_handler/validators.py
marketplace_handler/wb.py
marketplace_handler/yandex.py
marketplace_handler-3.0.16.dist-info/METADATA
marketplace_handler-3.0.16.dist-info/WHEEL
marketplace_handler-3.0.16.dist-info/top_level.txt
marketplace_handler-3.0.16.dist-info/RECORD
