Metadata-Version: 2.1
Name: marketplace_handler
Version: 3.0.16
Summary: Module to interact with marketplaces
Home-page: https://github.com/derijablya/marketplace-interface
Author: derijabyla
Author-email: dulugov@gmail.com
Requires-Dist: pydantic >=2.6.1
Requires-Dist: requests >=2.31.0
